odoo/addons/l10n_br_purchase_requisition/README.rst
odoo/addons/l10n_br_purchase_requisition/__init__.py
odoo/addons/l10n_br_purchase_requisition/__manifest__.py
odoo/addons/l10n_br_purchase_requisition/i18n/l10n_br_purchase_requisition.pot
odoo/addons/l10n_br_purchase_requisition/models/__init__.py
odoo/addons/l10n_br_purchase_requisition/models/purchase_order.py
odoo/addons/l10n_br_purchase_requisition/readme/CONFIGURE.md
odoo/addons/l10n_br_purchase_requisition/readme/CONTRIBUTORS.md
odoo/addons/l10n_br_purchase_requisition/readme/CREDITS.md
odoo/addons/l10n_br_purchase_requisition/readme/DESCRIPTION.md
odoo/addons/l10n_br_purchase_requisition/readme/INSTALL.md
odoo/addons/l10n_br_purchase_requisition/readme/USAGE.md
odoo/addons/l10n_br_purchase_requisition/static/description/icon.png
odoo/addons/l10n_br_purchase_requisition/static/description/index.html
odoo/addons/l10n_br_purchase_requisition/tests/__init__.py
odoo/addons/l10n_br_purchase_requisition/tests/test_l10n_br_purchase_requisition.py
odoo_addon_l10n_br_purchase_requisition-16.0.1.0.0.2.dist-info/METADATA
odoo_addon_l10n_br_purchase_requisition-16.0.1.0.0.2.dist-info/WHEEL
odoo_addon_l10n_br_purchase_requisition-16.0.1.0.0.2.dist-info/top_level.txt
odoo_addon_l10n_br_purchase_requisition-16.0.1.0.0.2.dist-info/RECORD
